{
    "1": {
        "enabled": false,
        "ntfy": [
            "test"
        ],
        "querys": [
            {
                "category_ids": null,
                "condition": null,
                "is_shippable": true,
                "keywords": "Psvita",
                "latitude": null,
                "longitude": null,
                "max_sale_price": "150",
                "order_by": "newest"
            }
        ]
    },
    "topic 2": {
        "enabled": true,
        "ntfy": [
            "test"
        ],
        "querys": [
            {
                "category_ids": null,
                "condition": null,
                "is_shippable": true,
                "keywords": "Psvita",
                "latitude": null,
                "longitude": null,
                "max_sale_price": "150",
                "min_sale_price": "30",
                "order_by": "newest"
            }
        ]
    },
    "topic 3": {
        "enabled": false,
        "ntfy": [],
        "querys": []
    }
}